[ { "chaine": { "nom":"CANAL-D SD(FR)","url": "http://206.212.244.71:8080/live/BRIDGITS@YAHOO.COM/BRIDGITS@2022/57479.m3u8" }},
  { "chaine": { "nom":"AL MAJD DOC","url": "http://vip.sibfungold.org:8080/live/hmx.oscam/FRtgBhh521&type/51443.m3u8" }},
  { "chaine": { "nom":"TEEN DOC(AR)","url": "http://ch14.tv/live/ch4teendoc/playlist.m3u8" }}, 
  { "chaine": { "nom":"KTV ARABI DOC","url": "https://kwtktvata.cdn.mangomolo.com/ktva/smil:tktva.stream.smil/chunklist.m3u8" }},
  { "chaine": { "nom":"ALJAZEERA DOC(AR)","url": "https://live-hls-apps-ajd-fa.getaj.net/AJD/index.m3u8" }},
  { "chaine": { "nom":"DW ARABIC(AR)","url": "https://dwamdstream103.akamaized.net/hls/live/2015526/dwstream103/master.m3u8" }},
  { "chaine": { "nom":"NATGEO ABUDHABI","url": "http://vip.sibfungold.org:8080/live/hmx.oscam/FRtgBhh521&type/51175.m3u8" }},
  { "chaine": { "nom":"OMAN THAKAFIA(AR)","url": "https://partwota.cdn.mgmlcdn.com/omcultural/smil:omcultural.stream.smil/chunklist.m3u8" }},
  { "chaine": { "nom":"EL SHARK DISCOVERY(AR)","url": "https://svs.itworkscdn.net/asharqdiscoverylive/asharqd.smil/playlist_dvr.m3u8" }},
    { "chaine": { "nom":"YEMEN DOCUMENTARY(AR)","url": "http://vip.sibfungold.org:8080/live/hmx.oscam/FRtgBhh521&type/56852.m3u8" }},
  { "chaine": { "nom":"ARTE HD","url": "http://vip.sibfungold.org:8080/live/hmx.oscam/FRtgBhh521&type/373.m3u8" }},
  { "chaine": { "nom":"TLC(FRANCE)","url": "http://vip.sibfungold.org:8080/live/hmx.oscam/FRtgBhh521&type/110.m3u8" }},
  { "chaine": { "nom":"TLC(AR)","url": "http://vip.sibfungold.org:8080/live/hmx.oscam/FRtgBhh521&type/51138.m3u8" }},
  { "chaine": { "nom":"ENQUETE DE CHOC","url": "https://amg01796-fastmediabackbo-enquetesdechoc-samsungfr-s0s2i.amagi.tv/playlist/amg01796-fastmediabackbo-enquetesdechoc-samsungfr/playlist.m3u8" }},
  { "chaine": { "nom":"ANIMAL PLANET ARABIC","url": "http://vip.sibfungold.org:8080/live/hmx.oscam/FRtgBhh521&type/50853.m3u8" }},
  { "chaine": { "nom":"PLUTOTV:ANIMAUX","url": "http://vip.sibfungold.org:8080/live/hmx.oscam/FRtgBhh521&type/56615.m3u8" }},
  { "chaine": { "nom":"PLUTOTV:AVENTURE","url": "http://vip.sibfungold.org:8080/live/hmx.oscam/FRtgBhh521&type/56614.m3u8" }},
  { "chaine": { "nom":"CANAL + DOCS","url": "http://vipkentken.top:8080/live/VIP0122169789554500/41697895545736/132312.m3u8" }},
  { "chaine": { "nom":"CANAL + DOCS FHD","url": "http://vip.sibfungold.org:8080/live/hmx.oscam/FRtgBhh521&type/54509.m3u8" }},
  { "chaine": { "nom":"NATIONAL GEOGRAPHIC CHANNEL HD","url": "http://vipkentken.top:8080/live/VIP0122169789554500/41697895545736/511.m3u8" }},
  { "chaine": { "nom":"NATGEO FHD","url": "http://vip.sibfungold.org:8080/live/hmx.oscam/FRtgBhh521&type/4502.m3u8" }},
  { "chaine": { "nom":"NATGEO WILD HD","url": "http://vip.sibfungold.org:8080/live/hmx.oscam/FRtgBhh521&type/3397.m3u8" }},
  { "chaine": { "nom":"NATGEO WILD FR FHD","url": "http://vip.sibfungold.org:8080/live/hmx.oscam/FRtgBhh521/48679.m3u8" }},
  { "chaine": { "nom":"ANIMAUX HD","url": "http://vip.sibfungold.org:8080/live/hmx.oscam/FRtgBhh521&type/114.m3u8" }},
  { "chaine": { "nom":"CHASSE & PECHE","url": "http://vip.sibfungold.org:8080/live/hmx.oscam/FRtgBhh521/116.m3u8" }},
  { "chaine": { "nom":"CHASSE & PECHE FHD","url": "http://vip.sibfungold.org:8080/live/hmx.oscam/FRtgBhh521/52778.m3u8" }},
  { "chaine": { "nom":"TREK HD","url": "http://vip.sibfungold.org:8080/live/hmx.oscam/FRtgBhh521&type/3678.m3u8" }},  
  { "chaine": { "nom":"VOYAGE & SAVEUR","url": "https://cdn-uw2-prod.tsv2.amagi.tv/linear/amg01821-lovetvchannels-lovewinefrance-lgfr/playlist.m3u8" }},
  { "chaine": { "nom":"VOYAGE+","url": "https://streams2.sofast.tv/v1/master/611d79b11b77e2f571934fd80ca1413453772ac7/ff8d1526-e572-4bb5-8c93-560eb80115bf/manifest.m3u8" }},
  { "chaine": { "nom":"TRAVEL XP","url": "https://travelxp-travelxp-4-fr.rakuten.wurl.tv/playlist.m3u8" }},
  { "chaine": { "nom":"MAISON & TRAVAUX","url": "https://raw.githubusercontent.com/Sibprod/streams/main/ressources/dm/py/hls/maisonettravaux.m3u8" }},
  { "chaine": { "nom":"CHEFCLUB","url": "https://d19umdgd0zr2ln.cloudfront.net/v1/master/3722c60a815c199d9c0ef36c5b73da68a62b09d1/Chefclub-FR-prod/chc/ch/ch.m3u8?ads.device_did=%7BPSID%7D&ads.device_dnt=%7BTARGETOPT%7D&ads.app_domain=%7BAPP_DOMAIN%7D&ads.app_name=%7BAPP_NAME%7D&ads.consent=%7BTC_STRING%7D&ads.ssai_vendor=SSSLIVE&ads.service_id=FRBB3900001PZ" }},
  { "chaine": { "nom":"TV5 MONDE CHEFS","url": "  https://d17g2p9a7he1mu.cloudfront.net/v1/master/3722c60a815c199d9c0ef36c5b73da68a62b09d1/cc-b4dzadk8a25ad/tv5ch.m3u8?ads.device_did=%7BPSID%7D&ads.device_dnt=%7BTARGETOPT%7D&ads.app_domain=%7BAPP_DOMAIN%7D&ads.app_name=%7BAPP_NAME%7D&ads.consent=%7BTC_STRING%7D&ads.ssai_vendor=SSSLIVE&ads.service_id=FR1300003HM" }},
  { "chaine": { "nom":"TV5 STYLE","url": "https://ott.tv5monde.com/Content/HLS/Live/channel(style1)/variant.m3u8" }},
  { "chaine": { "nom":"CAP TERRE","url": "  https://amg01821-lovetvchannels-lovetheplanetfrsamsung-samsungfr-hfam1.amagi.tv/ts-eu-w1-n2/playlist/amg01821-lovetvchannels-lovetheplanetfrsamsung-samsungfr/playlist.m3u8?ads.app_domain=%7BAPP_DOMAIN%7D&ads.app_name=%7BAPP_NAME%7D&ads.coppa=0&ads.did=%7BPSID%7D&ads.dnt=%7BTARGETOPT%7D&ads.tc_string=%7BTC_STRING%7D" }},
  { "chaine": { "nom":"100% DOCS","url": "https://amg02162-newenconnect-amg02162c2-rakuten-us-1981.playouts.now.amagi.tv/playlist/amg02162-newenconnect-100pour100docs-rakutenus/playlist.m3u8" }},
  { "chaine": { "nom":"L'EFFET PAPILLON","url": "https://amg02162-newenconnect-amg02162c1-rakuten-us-1983.playouts.now.amagi.tv/playlist/amg02162-newenconnect-leffetpapillon-rakutenus/playlist.m3u8" }},
  { "chaine": { "nom":"DOC STORY","url": "https://amg01796-amg01796c4-samsung-fr-3183.playouts.now.amagi.tv/playlist/amg01796-fastmediafast-docstory-samsungfr/playlist.m3u8?ads.did=%7BPSID%7D&ads.dnt=%7BTARGETOPT%7D&ads.app_domain=%7BAPP_DOMAIN%7D&ads.app_name=%7BAPP_NAME%7D&ads.tc_string=%7BTC_STRING%7D&ads.coppa=0" }},
  { "chaine": { "nom":"DESTINATION NATURE","url": "https://d2cl8wi5f8zf1j.cloudfront.net/v1/master/3722c60a815c199d9c0ef36c5b73da68a62b09d1/cc-0ay35jkybhd8m/DestinationNature_FR.m3u8?ads.device_did=%7BPSID%7D&ads.device_dnt=%7BTARGETOPT%7D&ads.app_domain=%7BAPP_DOMAIN%7D&ads.app_name=%7BAPP_NAME%7D&ads.consent=%7BTC_STRING%7D&ads.ssai_vendor=SSSLIVE&ads.service_id=FRBC4000001IO" }},
  { "chaine": { "nom":"NATURE TIME","url": "https://amg00090-blueantmedia-naturetime-samsungfr-yakbf.amagi.tv/playlist/amg00090-blueantmedia-naturetime-samsungfr/playlist.m3u8?ads.did=%7BPSID%7D&ads.dnt=%7BTARGETOPT%7D&ads.app  _domain=%7BAPP_DOMAIN%7D&ads.app_name=%7BAPP_NAME%7D&ads.tc_string=%7BTC_STRING%7D&ads.coppa=0" }},
  { "chaine": { "nom":"USHUAIA TV","url": "http://vip.sibfungold.org:8080/live/hmx.oscam/FRtgBhh521&type/112.m3u8" }},
  { "chaine": { "nom":"DISCOVERY CHANNEL HD","url": "http://vip.sibfungold.org:8080/live/hmx.oscam/FRtgBhh521&type/109.m3u8" }}, 
  { "chaine": { "nom":"DISCOVERY INVESTIGATION","url": "http://vipkentken.top:8080/live/VIP0122169789554500/41697895545736/503.m3u8" }},
  { "chaine": { "nom":"SCIENCE & VIE TV HD","url": "http://vip.sibfungold.org:8080/live/hmx.oscam/FRtgBhh521&type/2662.m3u8" }},
  { "chaine": { "nom":"PLANETE+ HD","url": "http://vip.sibfungold.org:8080/live/hmx.oscam/FRtgBhh521&type/4494.m3u8" }},
  { "chaine": { "nom":"PLANETE+ AE HD","url": "http://vip.sibfungold.org:8080/live/hmx.oscam/FRtgBhh521&type/4495.m3u8" }},
  { "chaine": { "nom":"PLANETE+ CI","url": "http://vipkentken.top:8080/live/VIP0122169789554500/41697895545736/510.m3u8" }},
  { "chaine": { "nom":"CRIME DISTRICT HD","url": "http://vip.sibfungold.org:8080/live/hmx.oscam/FRtgBhh521&type/51046.m3u8" }},
  { "chaine": { "nom":"INTRO CRIME","url": "https://amg00711-zylo-amg00711c10-rakuten-fr-6731.playouts.now.amagi.tv/playlist.m3u8" }},
  { "chaine": { "nom":"BFM TV GRANDS REPORTAGES","url": "https://ncdn-live-bfm.pfd.sfr.net/shls/LIVE$BFM_GRANDSREPORTAGES/index.m3u8?start=LIVE&end=END" }},
  { "chaine": { "nom":"RMC DECOUVERTE HD","url": "http://vip.sibfungold.org:8080/live/hmx.oscam/FRtgBhh521&type/52783.m3u8" }},
  { "chaine": { "nom":"RMC ALERT SECOURS HD","url": "http://vip.sibfungold.org:8080/live/hmx.oscam/FRtgBhh521&type/56691.m3u8" }},
  { "chaine": { "nom":"RMC J'IRAI DORMIR CHEZ VOUS","url": "https://dltlq2xit8olv.cloudfront.net/v1/master/3722c60a815c199d9c0ef36c5b73da68a62b09d1/cc-htbn65lnpv00c/Jirai_dormir_chez_vous_FR.m3u8?ads.device_did=%7BPSID%7D&ads.device_dnt=%7BTARGETOPT%7D&ads.app_domain=%7BAPP_DOMAIN%7D&ads.app_name=%7BAPP_NAME%7D&ads.consent=%7BTC_STRING%7D&ads.ssai_vendor=SSSLIVE&ads.service_id=FRBD4800001P4" }},
  { "chaine": { "nom":"RMC MECANIC","url": "https://d31lyfwi8gzfyr.cloudfront.net/v1/master/3722c60a815c199d9c0ef36c5b73da68a62b09d1/cc-ebepfdmg74kzh/RMC_MECANIC_FR.m3u8?ads.device_did=%7BPSID%7D&ads.device_dnt=%7BTARGETOPT%7D&ads.app_domain=%7BAPP_DOMAIN%7D&ads.app_name=%7BAPP_NAME%7D&ads.consent=%7BTC_STRING%7D&ads.ssai_vendor=SSSLIVE&ads.service_id=FR300003ZB" }},
  { "chaine": { "nom":"RMC MYSTÈRE","url": "https://d2mey07nrym09f.cloudfront.net/v1/master/3722c60a815c199d9c0ef36c5b73da68a62b09d1/cc-zzv8u40ihzmq2/RMC_MYSTERE_FR.m3u8?ads.device_did=%7BPSID%7D&ads.device_dnt=%7BTARGETOPT%7D&ads.app_domain=%7BAPP_DOMAIN%7D&ads.app_name=%7BAPP_NAME%7D&ads.consent=%7BTC_STRING%7D&ads.ssai_vendor=SSSLIVE&ads.service_id=FR300006GFs.device_dnt=%7BTARGETOPT%7D&ads.app_domain=%7BAPP_DOMAIN%7D&ads.app_name=%7BAPP_NAME%7D&ads.consent=%7BTC_STRING%7D&ads.ssai_vendor=SSSLIVE&ads.service_id=FR700002UP" }},
  { "chaine": { "nom":"!E","url": "http://vip.sibfungold.org:8080/live/hmx.oscam/FRtgBhh521&type/49266.m3u8" }},
  { "chaine": { "nom":"MISSION INTERVENTION","url": "https://dmskmsump4xmr.cloudfront.net/v1/master/3722c60a815c199d9c0ef36c5b73da68a62b09d1/cc-xja0jm5a38uno/rl.m3u8?ads.device_did=%7BPSID%7D&ads.device_dnt=%7BTARGETOPT%7D&ads.app_domain=%7BAPP_DOMAIN%7D&ads.app_name=%7BAPP_NAME%7D&ads.consent=%7BTC_STRING%7D&ads.ssai_vendor=SSSLIVE&ads.service_id=FR700002UP" }},
  { "chaine": { "nom":"INCROYABLES FORTUNES","url": " https://dn8mc7o4f0o74.cloudfront.net/v1/master/3722c60a815c199d9c0ef36c5b73da68a62b09d1/cc-e2c0yg2t7bpaj/aildl.m3u8?ads.device_did=%7BPSID%7D&ads.device_dnt=%7BTARGETOPT%7D&ads.app_domain=%7BAPP_DOMAIN%7D&ads.app_name=%7BAPP_NAME%7D&ads.consent=%7BTC_STRING%7D&ads.ssai_vendor=SSSLIVE&ads.service_id=FR600001I2" }},
  { "chaine": { "nom":"ÉPICURIEUX","url":"https://d1dzvywp5tcxbn.cloudfront.net/v1/master/3722c60a815c199d9c0ef36c5b73da68a62b09d1/cc-ryq1as86j3gxc/epic.m3u8?ads.device_did=%7BPSID%7D&ads.device_dnt=%7BTARGETOPT%7D&ads.app_domain=%7BAPP_DOMAIN%7D&ads.app_name=%7BAPP_NAME%7D&ads.consent=%7BTC_STRING%7D&ads.ssai_vendor=SSSLIVE&ads.service_id=FRBD5100003TP" }},
  { "chaine": { "nom":"SEASONS + HD","url": "http://vip.sibfungold.org:8080/live/hmx.oscam/FRtgBhh521&type/2892.m3u8" }},
  { "chaine": { "nom":"HISTOIRE HD","url": "http://vip.sibfungold.org:8080/live/hmx.oscam/FRtgBhh521&type/53376.m3u8" }},
  { "chaine": { "nom":"TOUTE L'HISTOIRE HD","url": "http://vip.sibfungold.org:8080/live/hmx.oscam/FRtgBhh521&type/4496.m3u8" }}
]
